Workbook

Sheet BOM
A1: Firefly Project — Bill of Materials (DJI F330 + Naza-M Lite)
A2: Estimated prices. BRL = USD × exchange rate × Brazil market factor (see Assumptions sheet).
A4: # | B4: Group | C4: Component | D4: Specification | E4: Qty | F4: Unit price (USD) | G4: Subtotal (USD) | H4: Unit price (BRL) | I4: Subtotal (BRL) | J4: Source / notes
A5: Aircraft
A6: 1 | B6: Frame | C6: DJI F330 (Quad X), clone | D6: 330 mm wheelbase, PDB integrated in bottom plate | E6: 1 | F6: 15 | G6: =E6*F6 -> 15 | H6: =F6*Assumptions!$B$4*Assumptions!$B$5 -> 135.0756 | I6: =E6*H6 -> 135.0756 | J6: Estimate. Original DJI F330 discontinued; clone kits typical.
A7: 2 | B7: Flight controller | C7: DJI Naza-M Lite | D7: Main controller + PMU + LED module | E7: 1 | F7: 38.99 | G7: =E7*F7 -> 38.99 | H7: =F7*Assumptions!$B$4*Assumptions!$B$5 -> 351.10651 | I7: =E7*H7 -> 351.10651 | J7: GetFPV list price (out of stock on 2026-10-08). Discontinued; used market varies.
A8: 3 | B8: Motors | C8: Brushless 2212 920KV | D8: CW/CCW, 3S | E8: 4 | F8: 9 | G8: =E8*F8 -> 36 | H8: =F8*Assumptions!$B$4*Assumptions!$B$5 -> 81.04536 | I8: =E8*H8 -> 324.18144 | J8: Estimate, generic A2212 920KV.
A9: 4 | B9: ESCs | C9: EMAX SimonK 30A | D9: 2-4S, linear BEC 2A/5V | E9: 4 | F9: 12 | G9: =E9*F9 -> 48 | H9: =F9*Assumptions!$B$4*Assumptions!$B$5 -> 108.06048 | I9: =E9*H9 -> 432.24192 | J9: Estimate. Rating per EMAX SimonK datasheet in Hardware/datasheets.
A10: 5 | B10: Radio | C10: HotRC HT-10A 2.4 GHz | D10: 10-channel transmitter + receiver | E10: 1 | F10: 40 | G10: =E10*F10 -> 40 | H10: =F10*Assumptions!$B$4*Assumptions!$B$5 -> 360.2016 | I10: =E10*H10 -> 360.2016 | J10: Estimate.
A11: 6 | B11: Propellers | C11: 8045 CW/CCW | D11: Plastic, 8 in, sets of 1 CW + 1 CCW | E11: 4 | F11: 2 | G11: =E11*F11 -> 8 | H11: =F11*Assumptions!$B$4*Assumptions!$B$5 -> 18.01008 | I11: =E11*H11 -> 72.04032 | J11: Estimate. 2 pairs mounted + 2 spare pairs. Prop size not confirmed on the aircraft.
A12: 7 | B12: Battery | C12: LiPo 3S 2200 mAh 25C+ | D12: XT60 or T-plug | E12: 1 | F12: 22 | G12: =E12*F12 -> 22 | H12: =F12*Assumptions!$B$4*Assumptions!$B$5 -> 198.11088 | I12: =E12*H12 -> 198.11088 | J12: Estimate. ASSUMPTION: battery spec not documented; update to actual cells/capacity.
C13: Aircraft subtotal | G13: =SUM(G6:G12) -> 207.99 | I13: =SUM(I6:I12) -> 1872.9583
A15: Tools and support equipment
A16: 8 | B16: Tools | C16: LiPo balance charger | D16: IMAX B6 class, 1-6S | E16: 1 | F16: 25 | G16: =E16*F16 -> 25 | H16: =F16*Assumptions!$B$4*Assumptions!$B$5 -> 225.126 | I16: =E16*H16 -> 225.126 | J16: Estimate.
A17: 9 | B17: Tools | C17: LiPo cell checker | D17: 1-8S voltage display/alarm | E17: 1 | F17: 5 | G17: =E17*F17 -> 5 | H17: =F17*Assumptions!$B$4*Assumptions!$B$5 -> 45.0252 | I17: =E17*H17 -> 45.0252 | J17: Estimate. Used in component verification.
A18: 10 | B18: Tools | C18: Servo / ESC tester | D18: PWM 1000-2000 µs | E18: 1 | F18: 6 | G18: =E18*F18 -> 6 | H18: =F18*Assumptions!$B$4*Assumptions!$B$5 -> 54.03024 | I18: =E18*H18 -> 54.03024 | J18: Estimate. Used in motor/ESC verification.
C19: Tools subtotal | G19: =SUM(G16:G18) -> 36 | I19: =SUM(I16:I18) -> 324.18144
C21: TOTAL | G21: =G13+G19 -> 243.99 | I21: =I13+I19 -> 2197.1397

Sheet Assumptions
A1: Firefly Project — BOM assumptions
A3: Parameter | B3: Value | C3: Notes
A4: USD/BRL exchange rate | B4: 5.0028 | C4: Commercial rate on 2026-10-07 15:45 (renovainvest.com.br/dolar-hoje). Update before use.
A5: Brazil market factor | B5: 1.8 | C5: Multiplier over the converted USD price to approximate the Brazilian retail price (import tax, ICMS, shipping, reseller margin). Estimate; adjust to quotes from Mercado Livre or local stores.
A6: Price reference date | B6: 2026-10-08 | C6: USD prices are typical US retail values for generic/clone parts unless the Source column says otherwise.
A8: Legend
A9: Blue text on yellow fill = editable input. Black = formula. Green = link to this sheet.
